{
  "id": "_xdm.mixins.experienceevent-media-reporting",
  "$schema": "http://json-schema.org/draft-06/schema#",
  "title": "MediaReporting Interaction Details ",
  "type": "object",
  "meta:extensible": true,
  "meta:abstract": true,
  "meta:tags": {
    "industry": [
      "all"
    ]
  },
  "description": "Track interactions with media reporting.",
  "meta:status": "experimental",
  "meta:xdmType": "object",
  "properties": {
    "mediaReporting": {
      "type": "object",
      "description": "Media Reporting related fields.",
      "meta:xdmType": "object",
      "properties": {
        "playerEventDetails": {
          "title": "Player Event Details",
          "$ref": "../../datatypes/playereventdetails.schema.json",
          "description": "Player event details information related to the experience event.",
          "meta:xdmField": "xdm:playerEventDetails",
          "tagNumber": 1
        },
        "sessionDetails": {
          "title": "Session Details",
          "$ref": "../../datatypes/sessiondetails.schema.json",
          "description": "Session details information related to the experience event.",
          "meta:xdmField": "xdm:sessionDetails",
          "tagNumber": 2
        },
        "advertisingDetails": {
          "title": "Advertising Details",
          "$ref": "../../datatypes/advertisingdetails.schema.json",
          "description": "Advertising details information related to the experience event.",
          "meta:xdmField": "xdm:advertisingDetails",
          "tagNumber": 3
        },
        "advertisingPodDetails": {
          "title": "Advertising Pod Details",
          "$ref": "../../datatypes/advertisingpoddetails.schema.json",
          "description": "Advertising pod details information related to the experience event.",
          "meta:xdmField": "xdm:advertisingPodDetails",
          "tagNumber": 4
        },
        "chapterDetails": {
          "title": "Chapter Details",
          "$ref": "../../datatypes/chapterdetails.schema.json",
          "description": "Chapter details information related to the experience event.",
          "meta:xdmField": "xdm:chapterDetails",
          "tagNumber": 5
        },
        "errorDetails": {
          "title": "Error Details",
          "$ref": "../../datatypes/errordetails.schema.json",
          "description": "Error details information related to the experience event.",
          "meta:xdmField": "xdm:errorDetails",
          "tagNumber": 6
        },
        "qoeDataDetails": {
          "title": "Qoe Data Details",
          "$ref": "../../datatypes/qoedatadetails.schema.json",
          "description": "Qoe data details information related to the experience event.",
          "meta:xdmField": "xdm:qoeDataDetails",
          "tagNumber": 7
        },
        "states": {
          "title": "List Of States",
          "type": "array",
          "description": "The list of states.",
          "meta:xdmType": "array",
          "items": {
            "$ref": "../../datatypes/playerstatedata.schema.json",
            "tagNumber": 1
          },
          "meta:xdmField": "xdm:states",
          "tagNumber": 8
        }
      },
      "meta:xdmField": "xdm:mediaReporting",
      "tagNumber": 1
    }
  },
  "meta:xdmId": "https://ns.adobe.com/xdm/mixins/experienceevent-media-reporting",
  "meta:altId": "_xdm.mixins.experienceevent-media-reporting",
  "id": "_xdm.mixins.experienceevent-media-reporting"
}