{
  "id": "_xdm.classes.fsi.atm",
  "$schema": "http://json-schema.org/draft-06/schema#",
  "title": "ATM",
  "type": "object",
  "meta:extensible": true,
  "meta:abstract": true,
  "meta:tags": {
    "industry": [
      "financial_services"
    ]
  },
  "description": "For ATM information such as active status, addrerss, ID and name. ",
  "meta:status": "stable",
  "meta:createdDate": [
    "2020-11-19",
    "2020-08-10"
  ],
  "meta:titleId": [
    "atm##title##18971",
    "record##title##92641"
  ],
  "meta:descriptionId": [
    "atm##description##47581",
    "record##description##41201"
  ],
  "meta:xdmType": "object",
  "properties": {
    "_id": {
      "title": "Identifier",
      "type": "string",
      "format": "uri-reference",
      "description": "A unique identifier for the record.",
      "meta:titleId": "record##@id##title##80061",
      "meta:descriptionId": "record##@id##description##41711",
      "meta:xdmType": "string",
      "meta:xdmField": "@id",
      "tagNumber": 1
    },
    "isAtmActive": {
      "title": "Is ATM Active",
      "type": "boolean",
      "description": "Yes/no if the ATM is currently active.",
      "meta:titleId": "atm##xdm:isAtmActive##title##45381",
      "meta:descriptionId": "atm##xdm:isAtmActive##description##45871",
      "meta:xdmType": "boolean",
      "meta:xdmField": "xdm:isAtmActive",
      "tagNumber": 2
    },
    "atmAddress": {
      "title": "ATM Address",
      "$ref": "../../datatypes/demographic/address.schema.json",
      "description": "Physicial address where the ATM is located.",
      "meta:titleId": "atm##xdm:atmAddress##title##93221",
      "meta:descriptionId": "atm##xdm:atmAddress##description##22211",
      "meta:xdmField": "xdm:atmAddress",
      "tagNumber": 3
    },
    "atmID": {
      "title": "ATM ID",
      "type": "string",
      "description": "ID associated with the ATM.",
      "meta:titleId": "atm##xdm:atmID##title##85651",
      "meta:descriptionId": "atm##xdm:atmID##description##56031",
      "meta:xdmType": "string",
      "meta:xdmField": "xdm:atmID",
      "tagNumber": 4
    },
    "atmName": {
      "title": "ATM Name",
      "type": "string",
      "description": "Name associated with the ATM.",
      "meta:titleId": "atm##xdm:atmName##title##44321",
      "meta:descriptionId": "atm##xdm:atmName##description##1571",
      "meta:xdmType": "string",
      "meta:xdmField": "xdm:atmName",
      "tagNumber": 5
    }
  },
  "meta:xdmId": "https://ns.adobe.com/xdm/classes/fsi/atm",
  "meta:altId": "_xdm.classes.fsi.atm",
  "id": "_xdm.classes.fsi.atm"
}
