{
  "id": "_xdm.mixins.experienceevent-user-login-details",
  "$schema": "http://json-schema.org/draft-06/schema#",
  "title": "User Login Process",
  "type": "object",
  "meta:extensible": true,
  "meta:abstract": true,
  "meta:tags": {
    "industry": [
      "retail",
      "financial_services",
      "travel_and_hospitality",
      "telecom",
      "automotive",
      "education",
      "health_and_life_sciences",
      "high_tech",
      "manufacturing",
      "media_and_entertainment",
      "public_sector"
    ]
  },
  "description": "User login details such as login state, location, and type, as well as forgot username and password counts.",
  "meta:status": "stable",
  "meta:createdDate": "2021-01-15",
  "meta:titleId": "experienceevent-user-login-details##title##51971",
  "meta:descriptionId": "experienceevent-user-login-details##description##22841",
  "meta:xdmType": "object",
  "properties": {
    "userAccount": {
      "type": "object",
      "description": "Loyalty details, preferences, login processes, and other account preferences.",
      "meta:descriptionId": "experienceevent-user-login-details##xdm:userAccount##description##24221",
      "meta:xdmType": "object",
      "properties": {
        "accountSwitch": {
          "title": "Switch User Accounts",
          "type": "integer",
          "description": "Captures when a visitor switches their account during a visit.",
          "meta:titleId": "experienceevent-user-login-details##xdm:accountSwitch##title##79831",
          "meta:descriptionId": "experienceevent-user-login-details##xdm:accountSwitch##description##9431",
          "meta:xdmType": "int",
          "meta:xdmField": "xdm:accountSwitch",
          "tagNumber": 1
        },
        "cookieConsentAccepted": {
          "title": "Cookie Consent Accepted",
          "type": "boolean",
          "description": "Tracked when a visitor opts-in to allowing cookies to be set within their browser.",
          "meta:titleId": "experienceevent-user-login-details##xdm:cookieConsentAccepted##title##51141",
          "meta:descriptionId": "experienceevent-user-login-details##xdm:cookieConsentAccepted##description##7511",
          "meta:xdmType": "boolean",
          "meta:xdmField": "xdm:cookieConsentAccepted",
          "tagNumber": 2
        },
        "cookieConsentViewed": {
          "title": "Cookie Consent Viewed",
          "type": "integer",
          "description": "Tracked when a visitor views the cookie consent information.",
          "meta:titleId": "experienceevent-user-login-details##xdm:cookieConsentViewed##title##72801",
          "meta:descriptionId": "experienceevent-user-login-details##xdm:cookieConsentViewed##description##99541",
          "meta:xdmType": "int",
          "meta:xdmField": "xdm:cookieConsentViewed",
          "tagNumber": 3
        },
        "forgotPassword": {
          "title": "Forgot Password",
          "type": "integer",
          "description": "Counter event when a visitor begins the forgot password process.",
          "meta:titleId": "experienceevent-user-login-details##xdm:forgotPassword##title##82391",
          "meta:descriptionId": "experienceevent-user-login-details##xdm:forgotPassword##description##77861",
          "meta:xdmType": "int",
          "meta:xdmField": "xdm:forgotPassword",
          "tagNumber": 4
        },
        "forgotUsername": {
          "title": "Forgot Username",
          "type": "integer",
          "description": "Counter event when a visitor begins the forgot username process.",
          "meta:titleId": "experienceevent-user-login-details##xdm:forgotUsername##title##71571",
          "meta:descriptionId": "experienceevent-user-login-details##xdm:forgotUsername##description##29401",
          "meta:xdmType": "int",
          "meta:xdmField": "xdm:forgotUsername",
          "tagNumber": 5
        },
        "login": {
          "title": "Visitor Login",
          "type": "integer",
          "description": "Counter event indicating a successful visitor login.",
          "meta:titleId": "experienceevent-user-login-details##xdm:login##title##9611",
          "meta:descriptionId": "experienceevent-user-login-details##xdm:login##description##17561",
          "meta:xdmType": "int",
          "meta:xdmField": "xdm:login",
          "tagNumber": 6
        },
        "loginBiometric": {
          "title": "Biometric Authentication",
          "type": "boolean",
          "description": "Flag determining if the user has used a biometric authentication process to login.",
          "meta:titleId": "experienceevent-user-login-details##xdm:loginBiometric##title##77011",
          "meta:descriptionId": "experienceevent-user-login-details##xdm:loginBiometric##description##70331",
          "meta:xdmType": "boolean",
          "meta:xdmField": "xdm:loginBiometric",
          "tagNumber": 7
        },
        "loginFailure": {
          "title": "Visitor Login Failure",
          "type": "integer",
          "description": "Counter event indicating a failed visitor login attempt.",
          "meta:titleId": "experienceevent-user-login-details##xdm:loginFailure##title##50511",
          "meta:descriptionId": "experienceevent-user-login-details##xdm:loginFailure##description##49331",
          "meta:xdmType": "int",
          "meta:xdmField": "xdm:loginFailure",
          "tagNumber": 8
        },
        "loginLocation": {
          "title": "Login Page Location",
          "type": "string",
          "description": "When multiple login locations exist on the page, this value should be used to identify the specific location the user used for login",
          "meta:titleId": "experienceevent-user-login-details##xdm:loginLocation##title##48691",
          "meta:descriptionId": "experienceevent-user-login-details##xdm:loginLocation##description##83411",
          "meta:xdmType": "string",
          "meta:xdmField": "xdm:loginLocation",
          "tagNumber": 9
        },
        "loginKeychain": {
          "title": "Keychain ",
          "type": "boolean",
          "description": "Flag determining if the user has used a keychain authentication process to login.",
          "meta:titleId": "experienceevent-user-login-details##xdm:loginKeychain##title##97921",
          "meta:descriptionId": "experienceevent-user-login-details##xdm:loginKeychain##description##4601",
          "meta:xdmType": "boolean",
          "meta:xdmField": "xdm:loginKeychain",
          "tagNumber": 10
        },
        "loginMultiFactor": {
          "title": "Multi-Factor Authentication",
          "type": "boolean",
          "description": "Flag determining if the user has used a multi-factor authentication process to login.",
          "meta:titleId": "experienceevent-user-login-details##xdm:loginMultiFactor##title##51661",
          "meta:descriptionId": "experienceevent-user-login-details##xdm:loginMultiFactor##description##16611",
          "meta:xdmType": "boolean",
          "meta:xdmField": "xdm:loginMultiFactor",
          "tagNumber": 11
        },
        "loginStatus": {
          "title": "Login Status",
          "type": "string",
          "description": "Used to track the current login status for site visitors, regardless of whether login occurred as a result of a login during the current session or a previous session as identified by a cookie value. ",
          "meta:titleId": "experienceevent-user-login-details##xdm:loginStatus##title##9661",
          "meta:descriptionId": "experienceevent-user-login-details##xdm:loginStatus##description##17931",
          "meta:xdmType": "string",
          "meta:xdmField": "xdm:loginStatus",
          "tagNumber": 12
        },
        "loginThirdParty": {
          "title": "Login with Third Party",
          "type": "integer",
          "description": "Counter event that is incremented when a visitor has used another login network to authenticate, such as Apple, Facebook, or Google.",
          "meta:titleId": "experienceevent-user-login-details##xdm:loginThirdParty##title##77121",
          "meta:descriptionId": "experienceevent-user-login-details##xdm:loginThirdParty##description##10781",
          "meta:xdmType": "int",
          "meta:xdmField": "xdm:loginThirdParty",
          "tagNumber": 13
        },
        "loginThirdPartySite": {
          "title": "Third Party Login Site",
          "type": "string",
          "description": "Tracks the site used to authetnicate when a third-party sign-in event is tracked.",
          "meta:titleId": "experienceevent-user-login-details##xdm:loginThirdPartySite##title##82101",
          "meta:descriptionId": "experienceevent-user-login-details##xdm:loginThirdPartySite##description##54831",
          "meta:xdmType": "string",
          "meta:xdmField": "xdm:loginThirdPartySite",
          "tagNumber": 14
        },
        "loginType": {
          "title": "User Login Type",
          "type": "string",
          "description": "Email address vs social login",
          "meta:titleId": "experienceevent-user-login-details##xdm:loginType##title##59801",
          "meta:descriptionId": "experienceevent-user-login-details##xdm:loginType##description##67841",
          "meta:xdmType": "string",
          "meta:xdmField": "xdm:loginType",
          "tagNumber": 15
        },
        "logout": {
          "title": "Visitor Logout",
          "type": "integer",
          "description": "Counter event indicating a successful visitor logout.",
          "meta:titleId": "experienceevent-user-login-details##xdm:logout##title##30251",
          "meta:descriptionId": "experienceevent-user-login-details##xdm:logout##description##9381",
          "meta:xdmType": "int",
          "meta:xdmField": "xdm:logout",
          "tagNumber": 16
        },
        "resetPassword": {
          "title": "Reset Password",
          "type": "integer",
          "description": "Counter event when a visitor begins the reset password process.",
          "meta:titleId": "experienceevent-user-login-details##xdm:resetPassword##title##48211",
          "meta:descriptionId": "experienceevent-user-login-details##xdm:resetPassword##description##26071",
          "meta:xdmType": "int",
          "meta:xdmField": "xdm:resetPassword",
          "tagNumber": 17
        },
        "sessionTimeout": {
          "title": "Session Timeout",
          "type": "integer",
          "description": "Tracked when a visitor has an authenticated session that is automatically logged out after a predetermined amount of time.",
          "meta:titleId": "experienceevent-user-login-details##xdm:sessionTimeout##title##9111",
          "meta:descriptionId": "experienceevent-user-login-details##xdm:sessionTimeout##description##34201",
          "meta:xdmType": "int",
          "meta:xdmField": "xdm:sessionTimeout",
          "tagNumber": 18
        },
        "updateProfile": {
          "title": "Account Profile Update",
          "type": "integer",
          "description": "Counter event indicating a user has updated their account profile.",
          "meta:titleId": "experienceevent-user-login-details##xdm:updateProfile##title##26881",
          "meta:descriptionId": "experienceevent-user-login-details##xdm:updateProfile##description##78111",
          "meta:xdmType": "int",
          "meta:xdmField": "xdm:updateProfile",
          "tagNumber": 19
        }
      },
      "meta:xdmField": "xdm:userAccount",
      "tagNumber": 1
    }
  },
  "meta:xdmId": "https://ns.adobe.com/xdm/mixins/experienceevent-user-login-details",
  "meta:altId": "_xdm.mixins.experienceevent-user-login-details",
  "id": "_xdm.mixins.experienceevent-user-login-details"
}