{
  "id": "_xdm.mixins.experienceevent-bill-pay-details",
  "$schema": "http://json-schema.org/draft-06/schema#",
  "title": "Bill Pay Details",
  "type": "object",
  "meta:extensible": true,
  "meta:abstract": true,
  "meta:tags": {
    "industry": [
      "financial_services"
    ]
  },
  "description": "Bill pay details such as transaction information, service account ID, and balance.",
  "meta:status": "stable",
  "meta:xdmType": "object",
  "properties": {
    "personalFinances": {
      "type": "object",
      "meta:xdmType": "object",
      "properties": {
        "billPayDetails": {
          "type": "object",
          "meta:xdmType": "object",
          "properties": {
            "transaction": {
              "title": "Transaction",
              "$ref": "../../../datatypes/industry-verticals/transaction.schema.json",
              "description": "Extension of transaction data type.",
              "meta:xdmField": "xdm:transaction",
              "tagNumber": 2
            },
            "financialAccount": {
              "title": "Financial Account",
              "$ref": "../../../datatypes/industry-verticals/financial-account.schema.json",
              "description": "Extension of financialAccount data type.  Details the account to which the balance is being transferred.",
              "meta:xdmField": "xdm:financialAccount",
              "tagNumber": 3
            },
            "scheduledTransactionDate": {
              "title": "Scheduled Transaction Date",
              "type": "string",
              "format": "date-time",
              "description": "Records the scheduled date/time of the transaction.",
              "meta:xdmType": "date-time",
              "meta:xdmField": "xdm:scheduledTransactionDate",
              "tagNumber": 4
            },
            "serviceProvider": {
              "type": "object",
              "description": "Tracks all details related to a biller.",
              "meta:xdmType": "object",
              "properties": {
                "name": {
                  "title": "Service Provider Name",
                  "type": "string",
                  "description": "The name/nickname for the service provider.",
                  "meta:xdmType": "string",
                  "meta:xdmField": "xdm:name",
                  "tagNumber": 1
                },
                "userAccountID": {
                  "title": "User Account ID",
                  "type": "string",
                  "description": "The user account ID for the service provider.",
                  "meta:xdmType": "string",
                  "meta:xdmField": "xdm:userAccountID",
                  "tagNumber": 2
                }
              },
              "meta:xdmField": "xdm:serviceProvider",
              "tagNumber": 5
            }
          },
          "meta:xdmField": "xdm:billPayDetails",
          "tagNumber": 1
        }
      },
      "meta:xdmField": "xdm:personalFinances",
      "tagNumber": 1
    }
  },
  "meta:xdmId": "https://ns.adobe.com/xdm/mixins/experienceevent-bill-pay-details",
  "meta:altId": "_xdm.mixins.experienceevent-bill-pay-details",
  "id": "_xdm.mixins.experienceevent-bill-pay-details"
}
